expycted/__init__.py
expycted/internals/base.py
expycted/internals/filesystem.py
expycted/internals/function.py
expycted/internals/utils.py
expycted/internals/value.py
expycted-0.8.2.dist-info/LICENSE
expycted-0.8.2.dist-info/WHEEL
expycted-0.8.2.dist-info/METADATA
expycted-0.8.2.dist-info/RECORD
