Metadata-Version: 2.1
Name: expycted
Version: 0.8.2
Summary: Because tests should be easy to read
Home-page: https://github.com/bdsoha/expycted
License: MIT
Keywords: expect,expect-pattern,testing,test,matchers
Author: Dov Benyomin Sohacheski
Requires-Python: >=3.6,<4.0
Classifier: License :: OSI Approved :: MIT License
Classifier: Natural Language :: English
Classifier: Programming Language :: Python :: 3
Classifier: Programming Language :: Python :: 3.6
Classifier: Programming Language :: Python :: 3.7
Classifier: Programming Language :: Python :: 3.8
Classifier: Programming Language :: Python :: 3.9
Classifier: Programming Language :: Python :: 3.10
Classifier: Programming Language :: Python :: 3.11
Classifier: Programming Language :: Python :: 3
Classifier: Topic :: Software Development :: Libraries
Classifier: Topic :: Software Development :: Testing
Classifier: Typing :: Typed
Project-URL: Repository, https://github.com/bdsoha/expycted
